notework/ItemUtils.py
notework/__init__.py
notework/youzan/__init__.py
notework/youzan/dubbo.py
notework/youzan/items.py
notework/youzan/pdf2html.py
notework-0.0.26.dist-info/METADATA
notework-0.0.26.dist-info/WHEEL
notework-0.0.26.dist-info/top_level.txt
notework-0.0.26.dist-info/RECORD
