Metadata-Version: 2.1
Name: notework
Version: 0.0.26
Summary: notework
Home-page: https://github.com/1007530194
Author: euler
Author-email: 1007530194@qq.com
License: UNKNOWN
Platform: UNKNOWN
